{
  "_meta": {
    "version": "1.0.20250715",
    "generated": "2025-07-15T21:41:13.893Z",
    "url": "https://raw.githubusercontent.com/osmlab/name-suggestion-index/main/dist/presets/nsi-id-presets.json",
    "hash": "2005ef7cb7c8a56b5f0394ee09c3068b"
  },
  "presets": {
    "man_made/flagpole/lgbtpride-e5dc93": {
      "name": "LGBT Pride",
      "locationSet": {"include": ["001"]},
      "icon": "maki-embassy",
      "geometry": ["point", "vertex"],
      "matchScore": 2,
      "imageURL": "https://commons.wikimedia.org/wiki/Special:FilePath/Gay Pride Flag.svg",
      "terms": [
        "gay",
        "gay pride",
        "lgbt",
        "lgbt pride",
        "lgbtq",
        "pride",
        "rainbow"
      ],
      "tags": {"flag:wikidata": "Q51401", "man_made": "flagpole"},
      "addTags": {
        "flag:name": "LGBT Pride",
        "flag:type": "cultural",
        "flag:wikidata": "Q51401",
        "man_made": "flagpole",
        "subject": "LGBT Pride",
        "subject:wikidata": "Q51406"
      }
    }
  }
}
